[
    {
        "network_slug": "matic-mainnet",
        "name": "Matic Token",
        "slug": "matic",
        "stablecoin": false,
        "contract": "0x0000000000000000000000000000000000001010",
        "decimals": 18,
        "site": "https://polygon.technology/",
        "network_url": "https://polygonscan.com/token/0x0000000000000000000000000000000000001010"
    },
    {
        "network_slug": "matic-mainnet",
        "name": "USD Coin",
        "slug": "usdc",
        "stablecoin": true,
        "contract": "0x2791bca1f2de4661ed88a30c99a7a9449aa84174",
        "decimals": 6,
        "site": "https://www.centre.io/",
        "network_url": "https://polygonscan.com/token/0x2791bca1f2de4661ed88a30c99a7a9449aa84174"
    },
    {
        "network_slug": "matic-mainnet",
        "name": "ChainLink Token",
        "slug": "link",
        "stablecoin": false,
        "contract": "0x53e0bca35ec356bd5dddfebbd1fc0fd03fabad39",
        "decimals": 18,
        "site": "https://chain.link/",
        "network_url": "https://polygonscan.com/token/0x53e0bca35ec356bd5dddfebbd1fc0fd03fabad39"
    },
    {
        "network_slug": "matic-mainnet",
        "name": "Decentraland",
        "slug": "mana",
        "stablecoin": false,
        "contract": "0xa1c57f48f0deb89f569dfbe6e2b7f46d33606fd4",
        "decimals": 18,
        "site": "https://decentraland.org/",
        "network_url": "https://polygonscan.com/token/0xa1c57f48f0deb89f569dfbe6e2b7f46d33606fd4"
    },
    {
        "network_slug": "matic-mainnet",
        "name": "Uniswap",
        "slug": "uni",
        "stablecoin": false,
        "contract": "0xb33eaad8d922b1083446dc23f610c2567fb5180f",
        "decimals": 18,
        "site": "https://uniswap.org/",
        "network_url": "https://polygonscan.com/token/0xb33eaad8d922b1083446dc23f610c2567fb5180f"
    },
    {
        "network_slug": "matic-mainnet",
        "name": "Graph Token",
        "slug": "grt",
        "stablecoin": false,
        "contract": "0x5fe2b58c013d7601147dcdd68c143a77499f5531",
        "decimals": 18,
        "site": "https://thegraph.com/",
        "network_url": "https://polygonscan.com/token/0x5fe2b58c013d7601147dcdd68c143a77499f5531"
    },
    {
        "network_slug": "matic-mainnet",
        "name": "Aave",
        "slug": "aave",
        "stablecoin": false,
        "contract": "0xd6df932a45c0f255f85145f286ea0b292b21c90b",
        "decimals": 18,
        "site": "https://aave.com/",
        "network_url": "https://polygonscan.com/token/0xd6df932a45c0f255f85145f286ea0b292b21c90b"
    },
    {
        "network_slug": "matic-mainnet",
        "name": "Basic Authentication Token (BAT)",
        "slug": "bat",
        "stablecoin": false,
        "contract": "0x3cef98bb43d732e2f285ee605a8158cde967d219",
        "decimals": 18,
        "site": "https://basicattentiontoken.org/",
        "network_url": "https://polygonscan.com/token/0x3cef98bb43d732e2f285ee605a8158cde967d219"
    },
    {
        "network_slug": "matic-mainnet",
        "name": "Curve (CRV)",
        "slug": "crv",
        "stablecoin": false,
        "contract": "0x172370d5cd63279efa6d502dab29171933a610af",
        "decimals": 18,
        "site": "https://www.curve.fi/",
        "network_url": "https://polygonscan.com/token/0x172370d5cd63279efa6d502dab29171933a610af"
    },
    {
        "network_slug": "matic-mainnet",
        "name": "Sushi Token",
        "slug": "sushi",
        "stablecoin": false,
        "contract": "0x0b3f868e0be5597d5db7feb59e1cadbb0fdda50a",
        "decimals": 18,
        "site": "https://sushi.com/",
        "network_url": "https://polygonscan.com/token/0x0b3f868e0be5597d5db7feb59e1cadbb0fdda50a"
    },
    {
        "network_slug": "matic-mainnet",
        "name": "Sand",
        "slug": "sand",
        "stablecoin": false,
        "contract": "0xc6d54d2f624bc83815b49d9c2203b1330b841ca0",
        "decimals": 18,
        "site": "http://www.sandbox.game/",
        "network_url": "https://polygonscan.com/token/0xc6d54d2f624bc83815b49d9c2203b1330b841ca0"
    }
]